ctimer/__init__.py
ctimer/cli.py
ctimer/controller.py
ctimer/ctimer.py
ctimer/ctimer_db.py
ctimer/flashing_button.py
ctimer/model.py
ctimer/view.py
ctimer/visual/__init__.py
ctimer/visual/show_stats.py
pomodoro_ctimer-2.0.2.dist-info/AUTHORS.rst
pomodoro_ctimer-2.0.2.dist-info/LICENSE
pomodoro_ctimer-2.0.2.dist-info/METADATA
pomodoro_ctimer-2.0.2.dist-info/WHEEL
pomodoro_ctimer-2.0.2.dist-info/entry_points.txt
pomodoro_ctimer-2.0.2.dist-info/top_level.txt
pomodoro_ctimer-2.0.2.dist-info/RECORD
