Metadata-Version: 2.1
Name: pomodoro-ctimer
Version: 2.0.2
Summary: Pomodoro is a famous time management technique aka tomato clock. Pomodoro C-timer is written in python and tkinter. This is a well maintained project. Your contributions are welcome on github!
Home-page: https://github.com/zztin/pomodoro-ctimer
Author: Liting Chen
Author-email: litingchen16@gmail.com
License: Apache Software license
Keywords: timer,concentration,pomodoro,time management
Platform: UNKNOWN
Classifier: Development Status :: 2 - Pre-Alpha
Classifier: Intended Audience :: Developers
Classifier: License :: OSI Approved :: Apache Software License
Classifier: Natural Language :: English
Classifier: Programming Language :: Python :: 3
Classifier: Programming Language :: Python :: 3.5
Classifier: Programming Language :: Python :: 3.6
Classifier: Programming Language :: Python :: 3.7
Classifier: Programming Language :: Python :: 3.8
Classifier: Topic :: Office/Business :: Scheduling
Requires-Python: >=3.5
Requires-Dist: pandas
Requires-Dist: bokeh
Requires-Dist: calmap
Requires-Dist: matplotlib
